README.rst
setup.py
mobi_parse.egg-info/PKG-INFO
mobi_parse.egg-info/SOURCES.txt
mobi_parse.egg-info/dependency_links.txt
mobi_parse.egg-info/requires.txt
mobi_parse.egg-info/top_level.txt
mobiparse/__init__.py
mobiparse/lz77.py
mobiparse/utils.py