Metadata-Version: 1.0
Name: mobi-parse
Version: 1.0.2
Summary: mobi parse
Home-page: https://github.com/ericzyh/mobi-parse
Author: eric_zyh
Author-email: 8040334@qq.com
License: BSD License
Platform: all
